cppgrader/__init__.py
cppgrader/__main__.py
cppgrader/app.py
cppgrader/components/AutoBuilder.py
cppgrader/components/AutoFilter.py
cppgrader/components/AutoReporter.py
cppgrader/components/ManualGrader.py
cppgrader/components/__init__.py
cppgrader/tools/__init__.py
cppgrader/tools/antiplag/__init__.py
cppgrader/tools/antiplag/__main__.py
cppgrader/tools/antiplag/antiplag.py
canvas_cppgrader-1.1.2.dist-info/METADATA
canvas_cppgrader-1.1.2.dist-info/WHEEL
canvas_cppgrader-1.1.2.dist-info/top_level.txt
canvas_cppgrader-1.1.2.dist-info/RECORD
