Metadata-Version: 2.1
Name: canvas-cppgrader
Version: 1.1.2
Summary: A toolkit to grade C/C++ submissions from canvas
Author: davidliyutong
Author-email: davidliyutong@sjtu.edu.cn
License: MIT Licence
Keywords: canvas,grader,cpp
Requires-Python: >=3.6
Requires-Dist: rarfile (==4.0)
Requires-Dist: tqdm (==4.56.0)
Requires-Dist: replit (==1.2.11)
Requires-Dist: typing-extensions (==3.7.4.3)
Requires-Dist: coloredlogs (==15.0.1)
